LICENSE
MANIFEST.in
README.md
setup.py
tspf.py
TSP_Framework.egg-info/PKG-INFO
TSP_Framework.egg-info/SOURCES.txt
TSP_Framework.egg-info/dependency_links.txt
TSP_Framework.egg-info/entry_points.txt
TSP_Framework.egg-info/not-zip-safe
TSP_Framework.egg-info/requires.txt
TSP_Framework.egg-info/top_level.txt
documentation/Manual.pdf
instances/1000-3.tsp
instances/1500-1.tsp
instances/2000-5.tsp
instances/2500-2.tsp
instances/3000-4.tsp
instances/att48.tsp
instances/att532.tsp
instances/berlin52.tsp
instances/burma14.tsp
instances/ch130.tsp
instances/eil51.tsp
instances/kroA100.tsp
instances/lin318.tsp
instances/qa194.tsp
instances/st70.tsp
instances/ulysses16.tsp
instances/ulysses22.tsp
instances/uy734.tsp
src/tspf/AlgorithmsOptions.py
src/tspf/TSPlibReader.py
src/tspf/Tour.py
src/tspf/Tsp.py
src/tspf/__init__.py
src/tspf/main.py
src/tspf/Algorithms/GeneticAlgorithm.py
src/tspf/Algorithms/IteratedLocalSearch.py
src/tspf/Algorithms/LocalSearch.py
src/tspf/Algorithms/Population.py
src/tspf/Algorithms/SimulatedAnnealing.py
src/tspf/Algorithms/__init__.py
src/tspf/Tools/__init__.py
src/tspf/Tools/gui.py
src/tspf/Tools/plot.py
src/tspf/Tools/utilities.py